polyglot_cli/__init__.py
polyglot_cli/__main__.py
polyglot_cli-0.1.0.dist-info/METADATA
polyglot_cli-0.1.0.dist-info/WHEEL
polyglot_cli-0.1.0.dist-info/entry_points.txt
polyglot_cli-0.1.0.dist-info/licenses/LICENSE
polyglot_cli-0.1.0.dist-info/RECORD
