Metadata-Version: 2.4
Name: polyglot-cli
Version: 0.1.0
Summary: AI-powered code translator using Claude Sonnet 4.5's extended thinking
Project-URL: Homepage, https://github.com/samar/polyglot-cli
Project-URL: Issues, https://github.com/samar/polyglot-cli/issues
Author-email: Samar <samar@example.com>
License-Expression: MIT
License-File: LICENSE
Keywords: ai,claude,cli,code-translation,polyglot,transpiler
Classifier: Development Status :: 4 - Beta
Classifier: Intended Audience :: Developers
Classifier: License :: OSI Approved :: MIT License
Classifier: Programming Language :: Python :: 3
Classifier: Programming Language :: Python :: 3.9
Classifier: Programming Language :: Python :: 3.10
Classifier: Programming Language :: Python :: 3.11
Classifier: Programming Language :: Python :: 3.12
Classifier: Topic :: Software Development :: Code Generators
Requires-Python: >=3.9
Requires-Dist: anthropic>=0.18.0
Requires-Dist: pygments>=2.15.0
Requires-Dist: rich>=13.0.0
Requires-Dist: typer>=0.9.0
